crash_test/__init__.py
crash_test/_version.py
crash_test/args_checker.py
crash_test/crashtest.py
crash_test/dependencies_checker.py
crash_test/error_codes.py
crash_test/error_logger.py
crash_test/script_selector.py
crash_test/scripts/npm_dependencies.sh
crash_test/scripts/python_dependencies.sh
crash_test/test_dir/npm/test_npm/.git/HEAD
crash_test/test_dir/npm/test_npm/.git/config
crash_test/test_dir/npm/test_npm/.git/description
crash_test/test_dir/npm/test_npm/.git/hooks/applypatch-msg.sample
crash_test/test_dir/npm/test_npm/.git/hooks/commit-msg.sample
crash_test/test_dir/npm/test_npm/.git/hooks/fsmonitor-watchman.sample
crash_test/test_dir/npm/test_npm/.git/hooks/post-update.sample
crash_test/test_dir/npm/test_npm/.git/hooks/pre-applypatch.sample
crash_test/test_dir/npm/test_npm/.git/hooks/pre-commit.sample
crash_test/test_dir/npm/test_npm/.git/hooks/pre-merge-commit.sample
crash_test/test_dir/npm/test_npm/.git/hooks/pre-push.sample
crash_test/test_dir/npm/test_npm/.git/hooks/pre-rebase.sample
crash_test/test_dir/npm/test_npm/.git/hooks/pre-receive.sample
crash_test/test_dir/npm/test_npm/.git/hooks/prepare-commit-msg.sample
crash_test/test_dir/npm/test_npm/.git/hooks/push-to-checkout.sample
crash_test/test_dir/npm/test_npm/.git/hooks/update.sample
crash_test/test_dir/npm/test_npm/.git/index
crash_test/test_dir/npm/test_npm/.git/info/exclude
crash_test/test_dir/npm/test_npm/.git/objects/26/4107447948de3019e28047b557f5caf7f0dfb0
crash_test/test_dir/npm/test_npm/.git/objects/82/62fbcc60f2f22f20b423e2c3e268769c43e6de
crash_test/test_dir/npm/test_npm/index.js
crash_test/test_dir/npm/test_npm/install.sh
crash_test/test_dir/npm/test_npm/node_modules/.package-lock.json
crash_test/test_dir/npm/test_npm/package.json
crash_test/test_dir/npm/test_npm/test/node_modules/.package-lock.json
crash_test/test_dir/npm/test_npm/test/script.js
crash_test/utils.py
crash_test_multipass-1.2.dist-info/LICENSE
crash_test_multipass-1.2.dist-info/METADATA
crash_test_multipass-1.2.dist-info/WHEEL
crash_test_multipass-1.2.dist-info/entry_points.txt
crash_test_multipass-1.2.dist-info/RECORD
