Metadata-Version: 2.1
Name: crash-test-multipass
Version: 1.2
Summary: A command-line tool to create a Multipass instance and transfer a project to test to the newly created instance
Home-page: https://github.com/utox39/crashtest
License: MIT
Author: utox39
Author-email: francescomoccaldi39@gmail.com
Requires-Python: >=3.10
Classifier: Intended Audience :: Developers
Classifier: License :: OSI Approved :: MIT License
Classifier: Operating System :: MacOS
Classifier: Operating System :: Microsoft :: Windows
Classifier: Operating System :: Unix
Classifier: Programming Language :: Python :: 3
Classifier: Programming Language :: Python :: 3.10
Classifier: Programming Language :: Python :: 3.11
Classifier: Programming Language :: Python :: 3.12
Classifier: Topic :: Utilities
Requires-Dist: colorama (>=0.4.6)
Project-URL: Bug Tracker, https://github.com/utox39/crashtest/issues
Project-URL: Repository, https://github.com/utox39/crashtest/issues
